baechu805_lotto/__init__.py
baechu805_lotto/draw.py
baechu805_lotto-0.2.0.dist-info/METADATA
baechu805_lotto-0.2.0.dist-info/WHEEL
baechu805_lotto-0.2.0.dist-info/top_level.txt
baechu805_lotto-0.2.0.dist-info/RECORD
