Metadata-Version: 2.1
Name: baechu805_lotto
Version: 0.2.0
Summary: Default template for PDM package
Author-email: baechu805 <bjoo606@naver.com>
License: MIT
Requires-Python: >=3.9
